mcp_lsq/__init__.py
mcp_lsq-0.1.2.dist-info/METADATA
mcp_lsq-0.1.2.dist-info/WHEEL
mcp_lsq-0.1.2.dist-info/entry_points.txt
mcp_lsq-0.1.2.dist-info/RECORD
