Metadata-Version: 2.4
Name: mcp-lsq
Version: 0.1.2
Summary: Add your description here
Author: dartou
Requires-Python: >=3.11
Requires-Dist: mcp[cli]>=1.10.0
Requires-Dist: requests
